CHANGES
LICENSE
MANIFEST.in
README.markdown
SetupConfig.py
SetupTools.py
TODO
setup.py
Cheetah.egg-info/PKG-INFO
Cheetah.egg-info/SOURCES.txt
Cheetah.egg-info/dependency_links.txt
Cheetah.egg-info/requires.txt
Cheetah.egg-info/top_level.txt
bin/cheetah
bin/cheetah-analyze
bin/cheetah-compile
cheetah/CacheRegion.py
cheetah/CacheStore.py
cheetah/CheetahWrapper.py
cheetah/Compiler.py
cheetah/DirectiveAnalyzer.py
cheetah/Django.py
cheetah/DummyTransaction.py
cheetah/ErrorCatchers.py
cheetah/FileUtils.py
cheetah/Filters.py
cheetah/ImportHooks.py
cheetah/ImportManager.py
cheetah/NameMapper.py
cheetah/Parser.py
cheetah/Servlet.py
cheetah/SettingsManager.py
cheetah/SourceReader.py
cheetah/Template.py
cheetah/TemplateCmdLineIface.py
cheetah/Unspecified.py
cheetah/Version.py
cheetah/__init__.py
cheetah/convertTmplPathToModuleName.py
cheetah/Macros/I18n.py
cheetah/Macros/__init__.py
cheetah/Templates/SkeletonPage.py
cheetah/Templates/SkeletonPage.tmpl
cheetah/Templates/_SkeletonPage.py
cheetah/Templates/__init__.py
cheetah/Tests/Analyzer.py
cheetah/Tests/CheetahWrapper.py
cheetah/Tests/Cheps.py
cheetah/Tests/Filters.py
cheetah/Tests/Misc.py
cheetah/Tests/NameMapper.py
cheetah/Tests/Parser.py
cheetah/Tests/Performance.py
cheetah/Tests/Regressions.py
cheetah/Tests/SyntaxAndOutput.py
cheetah/Tests/Template.py
cheetah/Tests/Test.py
cheetah/Tests/Unicode.py
cheetah/Tests/__init__.py
cheetah/Tests/xmlrunner.py
cheetah/Tools/CGITemplate.py
cheetah/Tools/MondoReport.py
cheetah/Tools/MondoReportDoc.txt
cheetah/Tools/RecursiveNull.py
cheetah/Tools/SiteHierarchy.py
cheetah/Tools/__init__.py
cheetah/Tools/turbocheetah/__init__.py
cheetah/Tools/turbocheetah/cheetahsupport.py
cheetah/Tools/turbocheetah/tests/__init__.py
cheetah/Tools/turbocheetah/tests/test_template.py
cheetah/Utils/Indenter.py
cheetah/Utils/Misc.py
cheetah/Utils/WebInputMixin.py
cheetah/Utils/__init__.py
cheetah/Utils/htmlDecode.py
cheetah/Utils/htmlEncode.py
cheetah/Utils/statprof.py
cheetah/c/_namemapper.c